pyreap-0.9.2.dist-info/licenses/LICENSE
reap/__init__.py
pyreap-0.9.2.dist-info/METADATA
pyreap-0.9.2.dist-info/WHEEL
pyreap-0.9.2.dist-info/top_level.txt
pyreap-0.9.2.dist-info/RECORD
