Metadata-Version: 2.4
Name: pyreap
Version: 0.9.2
Summary: Tool to automatically reap sub-processes.
Home-page: https://github.com/tgree/pyreap
Author: Terry Greeniaus
Author-email: terrygreeniaus@gmail.com
License: License :: OSI Approved :: MIT License
Keywords: pyreap reap subprocess
Classifier: Operating System :: POSIX
Classifier: Programming Language :: Python :: 3
Classifier: License :: OSI Approved :: MIT License
Requires-Python: >=3.6
License-File: LICENSE
Dynamic: license-file
